usentinel/__init__.py
usentinel/binaries.py
usentinel/cli.py
usentinel/main.py
usentinel/rules.py
usentinel/scanner.py
usentinel/semgrep_runner.py
usentinel/severity.py
usentinel/templates/report.html
usentinel-0.3.1.dist-info/licenses/LICENSE
usentinel_rules/__init__.py
usentinel_rules/core/heuristic/unity_core_heuristic.yaml
usentinel_rules/core/semgrep/unity.autorun.editor-hooks.yaml
usentinel_rules/core/semgrep/unity.crypto.weak-algos.yaml
usentinel_rules/core/semgrep/unity.deserialize.binaryformatter.yaml
usentinel_rules/core/semgrep/unity.net.discord-webhook.yaml
usentinel_rules/core/semgrep/unity.net.insecure-http.yaml
usentinel_rules/core/semgrep/unity.net.literal-url.yaml
usentinel_rules/core/semgrep/unity.proc.exec.process-start.yaml
usentinel_rules/core/semgrep/unity.reflection.using-namespace.yaml
usentinel-0.3.1.dist-info/METADATA
usentinel-0.3.1.dist-info/WHEEL
usentinel-0.3.1.dist-info/entry_points.txt
usentinel-0.3.1.dist-info/top_level.txt
usentinel-0.3.1.dist-info/RECORD
