Metadata-Version: 2.4
Name: usentinel
Version: 0.3.1
Summary: A lightweight CLI tool to audit Unity projects for risky code and binaries.
Author: Tianjiao Li
License: MIT License
Project-URL: Homepage, https://github.com/TLI-1994/Usentinel
Project-URL: Repository, https://github.com/TLI-1994/Usentinel
Project-URL: Issues, https://github.com/TLI-1994/Usentinel/issues
Keywords: unity,security,static-analysis,cli
Classifier: Development Status :: 3 - Alpha
Classifier: Environment :: Console
Classifier: Intended Audience :: Developers
Classifier: Programming Language :: Python :: 3
Classifier: Programming Language :: Python :: 3 :: Only
Classifier: License :: OSI Approved :: MIT License
Classifier: Operating System :: OS Independent
Classifier: Topic :: Security
Classifier: Topic :: Software Development :: Quality Assurance
Requires-Python: >=3.8
License-File: LICENSE
Requires-Dist: semgrep<=1.97,>=1.72; sys_platform != "win32"
Requires-Dist: semgrep>=1.132.0; sys_platform == "win32"
Requires-Dist: PyYAML>=6.0
Requires-Dist: certifi>=2023.0
Requires-Dist: Jinja2>=3.1
Requires-Dist: pygments>=2.16
Provides-Extra: test
Requires-Dist: pytest>=7.0; extra == "test"
Dynamic: license-file
